endoscopy/__init__.py
endoscopy/bounding_circle_detector.py
endoscopy/homography_estimator.py
endoscopy/utils/__init__.py
endoscopy/utils/circle_linear_system.py
endoscopy/utils/cropping.py
endoscopy/utils/helpers.py
endoscopy/utils/loader.py
endoscopy/utils/viz.py
endoscopy-0.1.5.dist-info/LICENSE
endoscopy-0.1.5.dist-info/METADATA
endoscopy-0.1.5.dist-info/WHEEL
endoscopy-0.1.5.dist-info/top_level.txt
endoscopy-0.1.5.dist-info/RECORD
