Metadata-Version: 2.1
Name: endoscopy
Version: 0.1.5
Summary: Image processing utilities for endoscopic images.
Home-page: https://github.com/RViMLab/endoscopy
Author: Martin Huber
Author-email: martin.huber@kcl.ac.uk
License: MIT
Project-URL: Bug Tracker, https://github.com/RViMLab/endoscopy/issues
Platform: UNKNOWN
Classifier: License :: OSI Approved :: MIT License
Classifier: Operating System :: OS Independent
Classifier: Programming Language :: Python :: 3.6
Classifier: Programming Language :: Python :: 3.7
Classifier: Programming Language :: Python :: 3.8
Classifier: Programming Language :: Python :: 3.9
License-File: LICENSE
Requires-Dist: torch (>=1.9)
Requires-Dist: kornia (>=0.6)
